{
  "id": "meek_mill",
  "name": "Meek Mill",
  "emoji": "🌊",
  "genre": "Melodic / R&B",
  "description": "Meek Mill tarzında profesyonel olarak ayarlanmış vokal zinciri.",
  "retune_speed": 0.5,
  "scale": "F Majör",
  "eq": {
    "low_shelf_hz": 60,
    "low_shelf_gain_db": 2.5,
    "high_shelf_hz": 12000,
    "high_shelf_gain_db": 3.5,
    "mid_peak_hz": 500,
    "mid_peak_gain_db": 0.1,
    "mid_peak_q": 0.65
  },
  "compression": {
    "threshold_db": -17.3,
    "ratio": 3.8,
    "attack_ms": 17.1,
    "release_ms": 224.8
  },
  "reverb": {
    "room_size": 0.61,
    "damping": 0.73,
    "wet_level": 0.44,
    "dry_level": 0.8,
    "width": 0.65
  },
  "tags": [
    "melodic",
    "smooth",
    "r&b",
    "türkçe"
  ]
}